dflopie.sv
// A Custom Width D Flip Flop module for delays
`timescale 1ns / 1ps

module dflopie #(
    parameter W = 1
) (
    input               clk_i, 
    input               rst_n_i,
    input               en_i,
    input       [W-1:0] data_in, 
    output      [W-1:0] data_out 
);
    
reg [W-1:0] data_out_reg;
always @(posedge clk_i or negedge rst_n_i) begin
    if(!rst_n_i) begin 
        data_out_reg <= 0;
    end
    else if(en_i) begin 
        data_out_reg <= data_in;
    end
end

assign data_out = data_out_reg;

endmodule

fir_filter.sv
// Main module for filter implementation 
`timescale 1ns / 1ps
module fir_filter #(
    parameter  INPUT_SIGNAL = 8, 
    parameter  CO_EFF_WIDTH = 8,
    parameter  OUTPUT_SIGNAL = 16,
    parameter  TAPS          = 7
) (
    input clk_i,
    input rst_n_i,
    input en_i,
    input signed [INPUT_SIGNAL-1:0] noisy_sig_i,
    output reg signed [OUTPUT_SIGNAL-1:0] filtered_res_o
);


// Wires for these co-efficient registers
wire signed [CO_EFF_WIDTH-1:0] co_eff [0:TAPS-1];
// Products
wire signed [OUTPUT_SIGNAL-1:0] pdt [0:TAPS-1];
// Tap Delays
wire signed [OUTPUT_SIGNAL-1:0] delay [1:TAPS-1];
// Adders
wire signed [OUTPUT_SIGNAL-1:0] sum [1:TAPS-1];

// Co-effs generated from Python file --> TODO: Automate this with a file
assign co_eff[0] = -1;
assign co_eff[1] = 23;
assign co_eff[2] = 33;
assign co_eff[3] = 38;
assign co_eff[4] = 33;
assign co_eff[5] = 23;
assign co_eff[6] = -1;

// // Multiply operation
genvar jj;
generate
    for (jj=0 ; jj<TAPS; jj++) begin 
        assign pdt[jj] = co_eff[jj] * noisy_sig_i;
    end
endgenerate

// Addition
genvar kk;
generate
    for (kk = 1; kk < TAPS ; kk++) begin 
        assign sum[kk] = delay[kk] + pdt[TAPS-(kk+1)];
    end
endgenerate

// Delay Line
genvar ll;
generate
    for (ll = 1; ll < TAPS-1 ; ll++) begin 
        dflopie #(.W(OUTPUT_SIGNAL)) delay_ll 
        (
            .data_in(sum[ll]),
            .data_out(delay[ll+1]),
            .clk_i(clk_i),
            .rst_n_i(rst_n_i),
            .en_i(en_i)
        );
    end
endgenerate

// Final delay element
dflopie #(.W(OUTPUT_SIGNAL)) delay_ll_d 
(
    .data_in(pdt[TAPS-1]),
    .data_out(delay[1]),
    .clk_i(clk_i),
    .rst_n_i(rst_n_i),
    .en_i(en_i)        
);

// Filtered Output = noisy_signal * filter_response
always @ (posedge clk_i or negedge rst_n_i) begin 
    if(!rst_n_i) 
        filtered_res_o <= 'b0;
    else
        filtered_res_o <= sum[6]; 
end

// Remove this part when synthesizing
initial begin
    $dumpfile("dump_fir.vcd");
    $dumpvars(0, fir_filter);
  end
endmodule

sim_build/dump_fir.vcd
$date
	Tue Nov  7 00:24:34 2023
$end
$version
	Icarus Verilog
$end
$timescale
	1ps
$end
$scope module fir_filter $end
$var wire 1 ! clk_i $end
$var wire 1 " en_i $end
$var wire 8 # noisy_sig_i [7:0] $end
$var wire 1 $ rst_n_i $end
$var reg 16 % filtered_res_o [15:0] $end
$scope begin genblk1[0] $end
$upscope $end
$scope begin genblk1[1] $end
$upscope $end
$scope begin genblk1[2] $end
$upscope $end
$scope begin genblk1[3] $end
$upscope $end
$scope begin genblk1[4] $end
$upscope $end
$scope begin genblk1[5] $end
$upscope $end
$scope begin genblk1[6] $end
$upscope $end
$scope begin genblk2[1] $end
$upscope $end
$scope begin genblk2[2] $end
$upscope $end
$scope begin genblk2[3] $end
$upscope $end
$scope begin genblk2[4] $end
$upscope $end
$scope begin genblk2[5] $end
$upscope $end
$scope begin genblk2[6] $end
$upscope $end
$scope begin genblk3[1] $end
$scope module delay_ll $end
$var wire 1 ! clk_i $end
$var wire 16 & data_in [15:0] $end
$var wire 1 " en_i $end
$var wire 1 $ rst_n_i $end
$var wire 16 ' data_out [15:0] $end
$var reg 16 ( data_out_reg [15:0] $end
$upscope $end
$upscope $end
$scope begin genblk3[2] $end
$scope module delay_ll $end
$var wire 1 ! clk_i $end
$var wire 16 ) data_in [15:0] $end
$var wire 1 " en_i $end
$var wire 1 $ rst_n_i $end
$var wire 16 * data_out [15:0] $end
$var reg 16 + data_out_reg [15:0] $end
$upscope $end
$upscope $end
$scope begin genblk3[3] $end
$scope module delay_ll $end
$var wire 1 ! clk_i $end
$var wire 16 , data_in [15:0] $end
$var wire 1 " en_i $end
$var wire 1 $ rst_n_i $end
$var wire 16 - data_out [15:0] $end
$var reg 16 . data_out_reg [15:0] $end
$upscope $end
$upscope $end
$scope begin genblk3[4] $end
$scope module delay_ll $end
$var wire 1 ! clk_i $end
$var wire 16 / data_in [15:0] $end
$var wire 1 " en_i $end
$var wire 1 $ rst_n_i $end
$var wire 16 0 data_out [15:0] $end
$var reg 16 1 data_out_reg [15:0] $end
$upscope $end
$upscope $end
$scope begin genblk3[5] $end
$scope module delay_ll $end
$var wire 1 ! clk_i $end
$var wire 16 2 data_in [15:0] $end
$var wire 1 " en_i $end
$var wire 1 $ rst_n_i $end
$var wire 16 3 data_out [15:0] $end
$var reg 16 4 data_out_reg [15:0] $end
$upscope $end
$upscope $end
$scope module delay_ll_d $end
$var wire 1 ! clk_i $end
$var wire 1 " en_i $end
$var wire 1 $ rst_n_i $end
$var wire 16 5 data_out [15:0] $end
$var wire 16 6 data_in [15:0] $end
$var reg 16 7 data_out_reg [15:0] $end
$upscope $end
$upscope $end
$enddefinitions $end
#0
$dumpvars
bx 7
b0 6
bx 5
bx 4
bx 3
bx 2
bx 1
bx 0
bx /
bx .
bx -
bx ,
bx +
bx *
bx )
bx (
bx '
bx &
bx %
z$
b0 #
z"
1!
$end
#500
0!
#1000
0"
1$
1!
#1500
0!
#2000
1!
#2500
0!
#3000
b0 )
b0 '
b0 (
b0 ,
b0 *
b0 +
b0 /
b0 -
b0 .
b0 2
b0 0
b0 1
b0 3
b0 4
b0 &
b0 5
b0 7
b0 %
0$
1!
#3500
0!
#4000
1!
#4500
0!
#5000
1$
1"
1!
#5500
0!
#6000
1!
#6500
0!
#7000
1!
#7500
0!
#8000
b11001100001 2
b100100100111 /
b101010001010 ,
b100100100111 )
b11001100001 &
b1111111110111001 6
b1000111 #
1!
#8500
0!
#9000
b1111111111011100 6
b100100 #
b101100000101 )
b11001100001 '
b11001100001 (
b111001111111 ,
b100100100111 *
b100100100111 +
b111100101110 /
b101010001010 -
b101010001010 .
b110001100011 2
b100100100111 0
b100100100111 1
b11001100001 3
b11001100001 4
b1011110101 &
b1111111110111001 5
b1111111110111001 7
b1111111110111001 %
1!
#9500
0!
#10000
b1111111110001111 6
b1110001 #
b11000111101 %
b101000000011 &
b1111111111011100 5
b1111111111011100 7
b110001100011 3
b110001100011 4
b1100101010101 2
b111100101110 0
b111100101110 1
b1110100010000 /
b111001111111 -
b111001111111 .
b1101111001011 ,
b101100000101 *
b101100000101 +
b1000110000110 )
b1011110101 '
b1011110101 (
1!
#10500
0!
#11000
b1111111111011101 6
b100011 #
b111010000110 )
b101000000011 '
b101000000011 (
b1011010111000 ,
b1000110000110 *
b1000110000110 +
b10000001001110 /
b1101111001011 -
b1101111001011 .
b10000000110101 2
b1110100010000 0
b1110100010000 1
b1100101010101 3
b1100101010101 4
b1010110100 &
b1111111110001111 5
b1111111110001111 7
b101111110010 %
1!
#11500
0!
#12000
b100 6
b11111100 #
b1100100110010 %
b1111111110000001 &
b1111111111011101 5
b1111111111011101 7
b10000000110101 3
b10000000110101 4
b1111111110010 2
b10000001001110 0
b10000001001110 1
b1011000110100 /
b1011010111000 -
b1011010111000 .
b110111101110 ,
b111010000110 *
b111010000110 +
b1000110000 )
b1010110100 '
b1010110100 (
1!
#12500
0!
#13000
b1001 6
b11110111 #
b1111111001011000 )
b1111111110000001 '
b1111111110000001 (
b11011010 ,
b1000110000 *
b1000110000 +
b110011000101 /
b110111101110 -
b110111101110 .
b1010101100101 2
b1011000110100 0
b1011000110100 1
b1111111110010 3
b1111111110010 4
b1111111100110101 &
b100 5
b100 7
b10000000111001 %
1!
#13500
0!
#14000
b1110001 6
b10001111 #
b1111111111011 %
b1111010111100010 &
b1001 5
b1001 7
b1010101100101 3
b1010101100101 4
b1010011110 2
b110011000101 0
b110011000101 1
b1111001001001001 /
b11011010 -
b11011010 .
b1110110110010010 ,
b1111111001011000 *
b1111111001011000 +
b1111000010100100 )
b1111111100110101 '
b1111111100110101 (
1!
#14500
0!
#15000
b110000 6
b11010000 #
b1110111110110010 )
b1111010111100010 '
b1111010111100010 (
b1110100110000100 ,
b1111000010100100 *
b1111000010100100 +
b1110011101100010 /
b1110110110010010 -
b1110110110010010 .
b1110110111111001 2
b1111001001001001 0
b1111001001001001 1
b1010011110 3
b1010011110 4
b1111110000100001 &
b1110001 5
b1110001 7
b1010111010110 %
1!
#15500
0!
#16000
b111101 6
b11000011 #
b1011001110 %
b1111101010110101 &
b110000 5
b110000 7
b1110110111111001 3
b1110110111111001 4
b1110000111100111 2
b1110011101100010 0
b1110011101100010 1
b1110000110100111 /
b1110100110000100 -
b1110100110000100 .
b1110011010100100 ,
b1110111110110010 *
b1110111110110010 +
b1111010001000100 )
b1111110000100001 '
b1111110000100001 (
1!
#16500
0!
#17000
b100000 6
b11100000 #
b1111011010010101 )
b1111101010110101 '
b1111101010110101 (
b1110111110000100 ,
b1111010001000100 *
b1111010001000100 +
b1110001010000100 /
b1110011010100100 -
b1110011010100100 .
b1101111011000111 2
b1110000110100111 0
b1110000110100111 1
b1110000111100111 3
b1110000111100111 4
b1111110101011101 &
b111101 5
b111101 7
b1110111000110110 %
1!
#17500
0!
#18000
b1111111110110111 6
b1001001 #
b1110001000000111 %
b11010101111 &
b100000 5
b100000 7
b1101111011000111 3
b1101111011000111 4
b1110100100010011 2
b1110001010000100 0
b1110001010000100 1
b1111100011101101 /
b1110111110000100 -
b1110111110000100 .
b101101011 ,
b1111011010010101 *
b1111011010010101 +
b11011000110 )
b1111110101011101 '
b1111110101011101 (
1!
#18500
0!
#19000
b1111111111011111 6
b100001 #
b101011110000 )
b11010101111 '
b11010101111 (
b101110101100 ,
b11011000110 *
b11011000110 +
b10110101100 /
b101101011 -
b101101011 .
b1111101111100100 2
b1111100011101101 0
b1111100011101101 1
b1110100100010011 3
b1110100100010011 4
b1010101110 &
b1111111110110111 5
b1111111110110111 7
b1101111001111110 %
1!
#19500
0!
#20000
b1111111110011011 6
b1100101 #
b1110100011110010 %
b100011110010 &
b1111111111011111 5
b1111111111011111 7
b1111101111100100 3
b1111101111100100 4
b111010111111 2
b10110101100 0
b10110101100 1
b1100010110001 /
b101110101100 -
b101110101100 .
b1100111101110 ,
b101011110000 *
b101011110000 +
b111110110011 )
b1010101110 '
b1010101110 (
1!
#20500
0!
#21000
b1111111111000001 6
b111111 #
b1000100010001 )
b100011110010 '
b100011110010 (
b1100100001101 ,
b111110110011 *
b111110110011 +
b10001000001101 /
b1100111101110 -
b1100111101110 .
b1111001011010 2
b1100010110001 0
b1100010110001 1
b111010111111 3
b111010111111 4
b10101000100 &
b1111111110011011 5
b1111111110011011 7
b1111101101111111 %
1!
#21500
0!
#22000
b1010 6
b11110110 #
b111010000000 %
b1111111011011011 &
b1111111111000001 5
b1111111111000001 7
b1111001011010 3
b1111001011010 4
b10000100100111 2
b10001000001101 0
b10001000001101 1
b1011111000011 /
b1100100001101 -
b1100100001101 .
b111110010101 ,
b1000100010001 *
b1000100010001 +
b1111111010 )
b10101000100 '
b10101000100 (
1!
#22500
0!
#23000
b1111111111110111 6
b1001 #
b100 )
b1111111011011011 '
b1111111011011011 (
b10101010000 ,
b1111111010 *
b1111111010 +
b1000010111110 /
b111110010101 -
b111110010101 .
b1100010010010 2
b1011111000011 0
b1011111000011 1
b10000100100111 3
b10000100100111 4
b11011001 &
b1010 5
b1010 7
b1111001100100 %
1!
#23500
0!
#24000
b1100101 6
b10011011 #
b10000100011110 %
b1111011011100100 &
b1111111111110111 5
b1111111111110111 7
b1100010010010 3
b1100010010010 4
b11110101011 2
b1000010111110 0
b1000010111110 1
b1111100001001011 /
b10101010000 -
b10101010000 .
b1111000100000110 ,
b100 *
b100 +
b1111001111010100 )
b11011001 '
b11011001 (
1!
#24500
0!
#25000
b1000100 6
b10111100 #
b1110111000100000 )
b1111011011100100 '
b1111011011100100 (
b1110100110111100 ,
b1111001111010100 *
b1111001111010100 +
b1110100001000010 /
b1111000100000110 -
b1111000100000110 .
b1111001000101111 2
b1111100001001011 0
b1111100001001011 1
b11110101011 3
b11110101011 4
b1111101001001001 &
b1100101 5
b1100101 7
b1100011110111 %
1!
#25500
0!
#26000
b110000 6
b11010000 #
b11111101111 %
b1111101111110100 &
b1000100 5
b1000100 7
b1111001000101111 3
b1111001000101111 4
b1110001111110010 2
b1110100001000010 0
b1110100001000010 1
b1110001110001100 /
b1110100110111100 -
b1110100110111100 .
b1110011100000000 ,
b1110111000100000 *
b1110111000100000 +
b1111010000011001 )
b1111101001001001 '
b1111101001001001 (
1!
#26500
0!
#27000
b111010 6
b11000110 #
b1111010001111010 )
b1111101111110100 '
b1111101111110100 (
b1110101101111101 ,
b1111010000011001 *
b1111010000011001 +
b1101111110000110 /
b1110011100000000 -
b1110011100000000 .
b1101111001010110 2
b1110001110001100 0
b1110001110001100 1
b1110001111110010 3
b1110001111110010 4
b1111101011111010 &
b110000 5
b110000 7
b1111001001011111 %
1!
#27500
0!
#28000
b1111111111000000 6
b1000000 #
b1110010000101100 %
b10111111010 &
b111010 5
b111010 7
b1101111001010110 3
b1101111001010110 4
b1110010101000110 2
b1101111110000110 0
b1101111110000110 1
b1111001110111101 /
b1110101101111101 -
b1110101101111101 .
b1111110111111010 ,
b1111010001111010 *
b1111010001111010 +
b1100111010 )
b1111101011111010 '
b1111101011111010 (
1!
#28500
0!
#29000
b1111111111011010 6
b100110 #
b101011100000 )
b10111111010 '
b10111111010 (
b100011011110 ,
b1100111010 *
b1100111010 +
b1011100000 /
b1111110111111010 -
b1111110111111010 .
b1111011100100111 2
b1111001110111101 0
b1111001110111101 1
b1110010101000110 3
b1110010101000110 4
b1100101010 &
b1111111111000000 5
b1111111111000000 7
b1101111000010110 %
1!
#29500
0!
#30000
b1111111110101110 6
b1010010 #
b1110010100100000 %
b11100111000 &
b1111111111011010 5
b1111111111011010 7
b1111011100100111 3
b1111011100100111 4
b101000111110 2
b1011100000 0
b1011100000 1
b1001101110000 /
b100011011110 -
b100011011110 .
b1011100001100 ,
b101011100000 *
b101011100000 +
b110110111100 )
b1100101010 '
b1100101010 (
1!
#30500
0!
#31000
b1111111110100101 6
b1011011 #
b1001011110011 )
b11100111000 '
b11100111000 (
b1101100111110 ,
b110110111100 *
b110110111100 +
b10001011000111 /
b1011100001100 -
b1011100001100 .
b1101110011101 2
b1001101110000 0
b1001101110000 1
b101000111110 3
b101000111110 4
b11111011011 &
b1111111110101110 5
b1111111110101110 7
b1111011011010101 %
1!
#31500
0!
#32000
b1010 6
b11110110 #
b100111100011 %
b1111111010111111 &
b1111111110100101 5
b1111111110100101 7
b1101110011101 3
b1101110011101 4
b10000111100001 2
b10001011000111 0
b10001011000111 1
b1100111110100 /
b1101100111110 -
b1101100111110 .
b1000101110111 ,
b1001011110011 *
b1001011110011 +
b11010010001 )
b11111011011 '
b11111011011 (
1!
#32500
0!
#33000
b1111111111101111 6
b10001 #
b11110000 )
b1111111010111111 '
b1111111010111111 (
b100100010111 ,
b11010010001 *
b11010010001 +
b1001110101000 /
b1000101110111 -
b1000101110111 .
b1101101111011 2
b1100111110100 0
b1100111110100 1
b10000111100001 3
b10000111100001 4
b110010001 &
b1010 5
b1010 7
b1101110100111 %
1!
#33500
0!
#34000
b1001111 6
b10110001 #
b10000111010000 %
b1111100011010110 &
b1111111111101111 5
b1111111111101111 7
b1101101111011 3
b1101101111011 4
b110010001111 2
b1001110101000 0
b1001110101000 1
b1111111011101000 /
b100100010111 -
b100100010111 .
b1111010100110110 ,
b11110000 *
b11110000 +
b1111011101100010 )
b110010001 '
b110010001 (
1!
#34500
0!
#35000
b1011001 6
b10100111 #
b1110110101011101 )
b1111100011010110 '
b1111100011010110 (
b1110101000101100 ,
b1111011101100010 *
b1111011101100010 +
b1110100110111101 /
b1111010100110110 -
b1111010100110110 .
b1111011011101001 2
b1111111011101000 0
b1111111011101000 1
b110010001111 3
b110010001111 4
b1111100001010000 &
b1001111 5
b1001111 7
b1101111001010 %
1!
#35500
0!
#36000
b100111 6
b11011001 #
b110011101000 %
b1111110011011000 &
b1011001 5
b1011001 7
b1111011011101001 3
b1111011011101001 4
b1110011000111100 2
b1110100110111101 0
b1110100110111101 1
b1110010100100101 /
b1110101000101100 -
b1110101000101100 .
b1110011110010011 ,
b1110110101011101 *
b1110110101011101 +
b1111001101001001 )
b1111100001010000 '
b1111100001010000 (
1!
#36500
0!
#37000
b1001010 6
b10110110 #
b1111001101001110 )
b1111110011011000 '
b1111110011011000 (
b1110100001001101 ,
b1111001101001001 *
b1111001101001001 +
b1101111000001001 /
b1110011110010011 -
b1110011110010011 .
b1101111001111111 2
b1110010100100101 0
b1110010100100101 1
b1110011000111100 3
b1110011000111100 4
b1111100110000001 &
b100111 5
b100111 7
b1111011100010000 %
1!
#37500
0!
#38000
b1111111111010011 6
b101101 #
b1110011010000110 %
b10001010101 &
b1001010 5
b1001010 7
b1101111001111111 3
b1101111001111111 4
b1110001000010100 2
b1101111000001001 0
b1101111000001001 1
b1110111000011010 /
b1110100001001101 -
b1110100001001101 .
b1111100111111100 ,
b1111001101001110 *
b1111001101001110 +
b1111111101001110 )
b1111100110000001 '
b1111100110000001 (
1!
#38500
0!
#39000
b1111111111001111 6
b110001 #
b101010100110 )
b10001010101 '
b10001010101 (
b11010010100 ,
b1111111101001110 *
b1111111101001110 +
b1001101 /
b1111100111111100 -
b1111100111111100 .
b1111001010000001 2
b1110111000011010 0
b1110111000011010 1
b1110001000010100 3
b1110001000010100 4
b10000111010 &
b1111111111010011 5
b1111111111010011 7
b1101111001010010 %
1!
#39500
0!
#40000
b1111111111000100 6
b111100 #
b1110000111100011 %
b10100110011 &
b1111111111001111 5
b1111111111001111 7
b1111001010000001 3
b1111001010000001 4
b10110110001 2
b1001101 0
b1001101 1
b111001010000 /
b11010010100 -
b11010010100 .
b1001110001110 ,
b101010100110 *
b101010100110 +
b101111110110 )
b10000111010 '
b10000111010 (
1!
#40500
0!
#41000
b1111111110010011 6
b1101101 #
b1001101000000 )
b10100110011 '
b10100110011 (
b1110000100100 ,
b101111110110 *
b101111110110 +
b10000110011011 /
b1001110001110 -
b1001110001110 .
b1100000011011 2
b111001010000 0
b111001010000 1
b10110110001 3
b10110110001 4
b100110001111 &
b1111111111000100 5
b1111111111000100 7
b1111001001000101 %
1!
#41500
0!
#42000
b1111111111111111 6
b1 #
b10101000100 %
b1111111110101010 &
b1111111110010011 5
b1111111110010011 7
b1100000011011 3
b1100000011011 4
b10000110110010 2
b10000110011011 0
b10000110011011 1
b1110001000101 /
b1110000100100 -
b1110000100100 .
b1001101100110 ,
b1001101000000 *
b1001101000000 +
b100110110000 )
b100110001111 '
b100110001111 (
1!
#42500
0!
#43000
b1111111111110001 6
b1111 #
b110011001 )
b1111111110101010 '
b1111111110101010 (
b101111101010 ,
b100110110000 *
b100110110000 +
b1010101010101 /
b1001101100110 -
b1001101100110 .
b1110110011110 2
b1110001000101 0
b1110001000101 1
b10000110110010 3
b10000110110010 4
b101011000 &
b1111111111111111 5
b1111111111111111 7
b1100000011010 %
1!
#43500
0!
#44000
b110001 6
b11001111 #
b10000110100011 %
b1111101110001010 &
b1111111111110001 5
b1111111111110001 7
b1110110011110 3
b1110110011110 4
b1000011101110 2
b1010101010101 0
b1010101010101 1
b10110011001 /
b101111101010 -
b101111101010 .
b1111101001010011 ,
b110011001 *
b110011001 +
b1111101100000111 )
b101011000 '
b101011000 (
1!
#44500
0!
#45000
b1101001 6
b10010111 #
b1110111000000001 )
b1111101110001010 '
b1111101110001010 (
b1110101101110001 ,
b1111101100000111 *
b1111101100000111 +
b1110110011001010 /
b1111101001010011 -
b1111101001010011 .
b1111110000101010 2
b10110011001 0
b10110011001 1
b1000011101110 3
b1000011101110 4
b1111011011000010 &
b110001 5
b110001 7
b1110111001111 %
1!
#45500
0!
#46000
b100011 6
b11011101 #
b1000101010111 %
b1111110101000100 &
b1101001 5
b1101001 7
b1111110000101010 3
b1111110000101010 4
b1110100110100101 2
b1110110011001010 0
b1110110011001010 1
b1110011011101110 /
b1110101101110001 -
b1110101101110001 .
b1110100011001111 ,
b1110111000000001 *
b1110111000000001 +
b1111001000111111 )
b1111011011000010 '
b1111011011000010 (
1!
#46500
0!
#47000
b1001110 6
b10110010 #
b1111001100110110 )
b1111110101000100 '
b1111110101000100 (
b1110011010101011 ,
b1111001000111111 *
b1111001000111111 +
b1101111011000001 /
b1110100011001111 -
b1110100011001111 .
b1101111111101100 2
b1110011011101110 0
b1110011011101110 1
b1110100110100101 3
b1110100110100101 4
b1111100100100001 &
b100011 5
b100011 7
b1111110001001101 %
1!
#47500
0!
#48000
b1111111111110000 6
b10000 #
b1110100111110011 %
b110111110 &
b1001110 5
b1001110 7
b1101111111101100 3
b1101111111101100 4
b1110000000110001 2
b1101111011000001 0
b1101111011000001 1
b1110100010111011 /
b1110011010101011 -
b1110011010101011 .
b1111010110010110 ,
b1111001100110110 *
b1111001100110110 +
b1111101100110001 )
b1111100100100001 '
b1111100100100001 (
1!
#48500
0!
#49000
b1111111111000011 6
b111101 #
b100110011011 )
b110111110 '
b110111110 (
b10000111111 ,
b1111101100110001 *
b1111101100110001 +
b1111110101110011 /
b1111010110010110 -
b1111010110010110 .
b1110111000110110 2
b1110100010111011 0
b1110100010111011 1
b1110000000110001 3
b1110000000110001 4
b10101101011 &
b1111111111110000 5
b1111111111110000 7
b1101111111011100 %
1!
#49500
0!
#50000
b1111111111010110 6
b101010 #
b1101111111110100 %
b1110001001 &
b1111111111000011 5
b1111111111000011 7
b1110111000110110 3
b1110111000110110 4
b100111001 2
b1111110101110011 0
b1111110101110011 1
b100110101001 /
b10000111111 -
b10000111111 .
b111111010111 ,
b100110011011 *
b100110011011 +
b101011010101 )
b10101101011 '
b10101101011 (
1!
#50500
0!
#51000
b1111111110001011 6
b1110101 #
b1001010011110 )
b1110001001 '
b1110001001 (
b1110000110011 ,
b101011010101 *
b101011010101 +
b1111011101100 /
b111111010111 -
b111111010111 .
b1010000101100 2
b100110101001 0
b100110101001 1
b100111001 3
b100111001 4
b101001011001 &
b1111111111010110 5
b1111111111010110 7
b1110111000001100 %
1!
#51500
0!
#52000
b1111111111101011 6
b10101 #
b11000100 %
b101101110 &
b1111111110001011 5
b1111111110001011 7
b1010000101100 3
b1010000101100 4
b10000011001111 2
b1111011101100 0
b1111011101100 1
b1111011101000 /
b1110000110011 -
b1110000110011 .
b1010110111100 ,
b1001010011110 *
b1001010011110 +
b110100001110 )
b101001011001 '
b101001011001 (
1!
#52500
0!
#53000
b1111111111111001 6
b111 #
b1001010101 )
b101101110 '
b101101110 (
b111000011000 ,
b110100001110 *
b110100001110 +
b1011010100011 /
b1010110111100 -
b1010110111100 .
b1111110001001 2
b1111011101000 0
b1111011101000 1
b10000011001111 3
b10000011001111 4
b10001100 &
b1111111111101011 5
b1111111111101011 7
b1010000010111 %
1!
#53500
0!
#54000
b10101 6
b11101011 #
b10000011001000 %
b1111111000010110 &
b1111111111111001 5
b1111111111111001 7
b1111110001001 3
b1111110001001 4
b1010011000000 2
b1011010100011 0
b1011010100011 1
b101101100011 /
b111000011000 -
b111000011000 .
b1111111100110111 ,
b1001010101 *
b1001010101 +
b1111110111010111 )
b10001100 '
b10001100 (
1!
#54500
0!
#55000
b1110000 6
b10010000 #
b1110111110100110 )
b1111111000010110 '
b1111111000010110 (
b1110110100110111 ,
b1111110111010111 *
b1111110111010111 +
b1111000011000111 /
b1111111100110111 -
b1111111100110111 .
b101010011 2
b101101100011 0
b101101100011 1
b1010011000000 3
b1010011000000 4
b1111011000000101 &
b10101 5
b10101 7
b1111110011110 %
1!
#55500
0!
#56000
b101001 6
b11010111 #
b1010100110000 %
b1111110011000001 &
b1110000 5
b1110000 7
b101010011 3
b101010011 4
b1110110100011000 2
b1111000011000111 0
b1111000011000111 1
b1110011111101110 /
b1110110100110111 -
b1110110100110111 .
b1110100110010000 ,
b1110111110100110 *
b1110111110100110 +
b1111000010111100 )
b1111011000000101 '
b1111011000000101 (
1!
#56500
0!
#57000
b1001001 6
b10110111 #
b1111001101011000 )
b1111110011000001 '
b1111110011000001 (
b1110010111100110 ,
b1111000010111100 *
b1111000010111100 +
b1110000000100111 /
b1110100110010000 -
b1110100110010000 .
b1110000101011111 2
b1110011111101110 0
b1110011111101110 1
b1110110100011000 3
b1110110100011000 4
b1111100110011010 &
b101001 5
b101001 7
b101111100 %
1!
#57500
0!
#58000
b10001 6
b11101111 #
b1110110101100001 %
b1111111011000010 &
b1001001 5
b1001001 7
b1110000101011111 3
b1110000101011111 4
b1101111010100000 2
b1110000000100111 0
b1110000000100111 1
b1110001110110101 /
b1110010111100110 -
b1110010111100110 .
b1111000011010010 ,
b1111001101011000 *
b1111001101011000 +
b1111011101101001 )
b1111100110011010 '
b1111100110011010 (
1!
#58500
0!
#59000
b1111111110111100 6
b1000100 #
b11110000110 )
b1111111011000010 '
b1111111011000010 (
b110000001 ,
b1111011101101001 *
b1111011101101001 +
b1111100110010110 /
b1111000011010010 -
b1111000011010010 .
b1110100111010001 2
b1110001110110101 0
b1110001110110101 1
b1101111010100000 3
b1101111010100000 4
b11000101101 &
b10001 5
b10001 7
b1110000101110000 %
1!
#59500
0!
#60000
b1111111111100001 6
b11111 #
b1101111001011100 %
b1010000101 &
b1111111110111100 5
b1111111110111100 7
b1110100111010001 3
b1110100111010001 4
b1111110001011111 2
b1111100110010110 0
b1111100110010110 1
b10110000000 /
b110000001 -
b110000001 .
b110000100000 ,
b11110000110 *
b11110000110 +
b101000101100 )
b11000101101 '
b11000101101 (
1!
#60500
0!
#61000
b1111111110010001 6
b1101111 #
b1000011010100 )
b1010000101 '
b1010000101 (
b1101010100110 ,
b101000101100 *
b101000101100 +
b1101001101111 /
b110000100000 -
b110000100000 .
b111101111001 2
b10110000000 0
b10110000000 1
b1111110001011111 3
b1111110001011111 4
b100111011010 &
b1111111111100001 5
b1111111111100001 7
b1110100110110010 %
1!
#61500
0!
#62000
b1111111111001111 6
b110001 #
b1111101111110000 %
b1111111000 &
b1111111110010001 5
b1111111110010001 7
b111101111001 3
b111101111001 4
b1111011010110 2
b1101001101111 0
b1101001101111 1
b10000011110111 /
b1101010100110 -
b1101010100110 .
b1100000011010 ,
b1000011010100 *
b1000011010100 +
b1000000101011 )
b100111011010 '
b100111011010 (
1!
#62500
0!
#63000
b1 6
b11111111 #
b1111010111 )
b1111111000 '
b1111111000 (
b1000000000101 ,
b1000000101011 *
b1000000101011 +
b1011111111001 /
b1100000011010 -
b1100000011010 .
b10000011100000 2
b10000011110111 0
b10000011110111 1
b1111011010110 3
b1111011010110 4
b1111111110111000 &
b1111111111001111 5
b1111111111001111 7
b111101001000 %
1!
#63500
0!
#64000
b1111111111111100 6
b100 #
b1111011010111 %
b1011101 &
b1 5
b1 7
b10000011100000 3
b10000011100000 4
b1100001010101 2
b1011111111001 0
b1011111111001 1
b1000010001001 /
b1000000000101 -
b1000000000101 .
b10001101111 ,
b1111010111 *
b1111010111 +
b111100 )
b1111111110111000 '
b1111111110111000 (
1!
#64500
0!
#65000
b1101100 6
b10010100 #
b1111001001110001 )
b1011101 '
b1011101 (
b1111000000110100 ,
b111100 *
b111100 +
b1111011010000011 /
b10001101111 -
b10001101111 .
b11011010101 2
b1000010001001 0
b1000010001001 1
b1100001010101 3
b1100001010101 4
b1111011001001000 &
b1111111111111100 5
b1111111111111100 7
b10000011011100 %
1!
#65500
0!
#66000
b111000 6
b11001000 #
b1100011000001 %
b1111101101100100 &
b1101100 5
b1101100 7
b11011010101 3
b11011010101 4
b1111000101111011 2
b1111011010000011 0
b1111011010000011 1
b1110100011111100 /
b1111000000110100 -
b1111000000110100 .
b1110101000100001 ,
b1111001001110001 *
b1111001001110001 +
b1110111100010000 )
b1111011001001000 '
b1111011001001000 (
1!
#66500
0!
#67000
b111101 6
b11000011 #
b1111001110000111 )
b1111101101100100 '
b1111101101100100 (
b1110011000000010 ,
b1110111100010000 *
b1110111100010000 +
b1110001001000100 /
b1110101000100001 -
b1110101000100001 .
b1110001110000001 2
b1110100011111100 0
b1110100011111100 1
b1111000101111011 3
b1111000101111011 4
b1111101010111101 &
b111000 5
b111000 7
b11100001101 %
1!
#67500
0!
#68000
b101111 6
b11010001 #
b1111000110111000 %
b1111110000000100 &
b111101 5
b111101 7
b1110001110000001 3
b1110001110000001 4
b1101111000001011 2
b1110001001000100 0
b1110001001000100 1
b1101111111110011 /
b1110011000000010 -
b1110011000000010 .
b1110110010001101 ,
b1111001110000111 *
b1111001110000111 +
b1111010010101110 )
b1111101010111101 '
b1111101010111101 (
1!
#68500
0!
#69000
b1111111110111110 6
b1000010 #
b10010000110 )
b1111110000000100 '
b1111110000000100 (
b1111111001111010 ,
b1111010010101110 *
b1111010010101110 +
b1111010100001111 /
b1110110010001101 -
b1110110010001101 .
b1110010111100001 2
b1101111111110011 0
b1101111111110011 1
b1101111000001011 3
b1101111000001011 4
b11000011101 &
b101111 5
b101111 7
b1110001110110000 %
1!
#69500
0!
